starknet_skproof/__init__.py
starknet_skproof/float_num/FloatNum.py
starknet_skproof/float_num/__init__.py
starknet_skproof/mlp/MLPClassifierProver.py
starknet_skproof/mlp/__init__.py
starknet_skproof-1.0.1.dist-info/METADATA
starknet_skproof-1.0.1.dist-info/WHEEL
starknet_skproof-1.0.1.dist-info/top_level.txt
starknet_skproof-1.0.1.dist-info/RECORD
