Metadata-Version: 2.1
Name: starknet-skproof
Version: 1.0.1
Summary: SciKit learn compatible library for generating ZK proofs of execution
Home-page: https://github.com/0x3327/Starknet-SKProof.git
Author: Boris Cvitak, 3327.io
Author-email: cvitak.boris@gmail.com
License: BSD 2-clause
Platform: UNKNOWN
Classifier: Development Status :: 1 - Planning
Classifier: Intended Audience :: Science/Research
Classifier: License :: OSI Approved :: BSD License
Classifier: Programming Language :: Python :: 3.10
Requires-Dist: numpy
Requires-Dist: scikit-learn
